sqlalchemy_fastmcp/__init__.py
sqlalchemy_fastmcp/__main__.py
sqlalchemy_fastmcp/_version.py
sqlalchemy_fastmcp/server.py
sqlalchemy_fastmcp/ssh_tunnel_manager.py
sqlalchemy_fastmcp/utils.py
sqlalchemy_fastmcp/drive/__init__.py
sqlalchemy_fastmcp/drive/base.py
sqlalchemy_fastmcp/drive/mysql.py
sqlalchemy_fastmcp/drive/postgresql.py
sqlalchemy_fastmcp/drive/sqlite.py
sqlalchemy_fastmcp/tools/__init__.py
sqlalchemy_fastmcp/tools/exec_query.py
sqlalchemy_fastmcp/tools/get_database_info.py
sqlalchemy_fastmcp/tools/get_ssh_tunnel_status.py
sqlalchemy_fastmcp/tools/set_database_source.py
sqlalchemy_fastmcp/tools/set_database_source_on_ssh.py
sqlalchemy_fastmcp/tools/show_databases.py
sqlalchemy_fastmcp/tools/show_tables.py
sqlalchemy_fastmcp/tools/stop_ssh_tunnel.py
sqlalchemy_fastmcp/tools/test_database_connection.py
sqlalchemy_fastmcp-1.2.9.dist-info/licenses/LICENSE
sqlalchemy_fastmcp-1.2.9.dist-info/METADATA
sqlalchemy_fastmcp-1.2.9.dist-info/WHEEL
sqlalchemy_fastmcp-1.2.9.dist-info/entry_points.txt
sqlalchemy_fastmcp-1.2.9.dist-info/top_level.txt
sqlalchemy_fastmcp-1.2.9.dist-info/RECORD
