Metadata-Version: 2.4
Name: sqlalchemy_fastmcp
Version: 1.2.9
Summary: SQLAlchemy MCP Server for manipulating databases
Author-email: ferock <ferock@gmail.com>
Requires-Python: >=3.12
License-File: LICENSE
Requires-Dist: fastmcp>=2.14.2
Requires-Dist: SQLAlchemy>=2.0.45
Requires-Dist: python-dotenv>=1.0.0
Requires-Dist: pymysql>=1.1.2
Requires-Dist: psycopg2-binary>=2.9.11
Requires-Dist: typer>=0.16.0
Requires-Dist: sshtunnel>=0.4.0
Requires-Dist: paramiko==3.5.1
Provides-Extra: dev
Requires-Dist: build; extra == "dev"
Requires-Dist: twine; extra == "dev"
Dynamic: license-file
